speedy_antlr_lua_parser-0.0.1.dist-info/RECORD
speedy_antlr_lua_parser-0.0.1.dist-info/LICENSE
speedy_antlr_lua_parser-0.0.1.dist-info/WHEEL
speedy_antlr_lua_parser-0.0.1.dist-info/top_level.txt
speedy_antlr_lua_parser-0.0.1.dist-info/METADATA
speedy_antlr_lua_parser/LuaLexer.py
speedy_antlr_lua_parser/sa_lua_cpp_parser.cpython-39-darwin.so
speedy_antlr_lua_parser/__init__.py
speedy_antlr_lua_parser/sa_lua.py
speedy_antlr_lua_parser/parse_chunk.py
speedy_antlr_lua_parser/LuaParser.py
speedy_antlr_lua_parser/LuaLexerBase.py
