Metadata-Version: 2.1
Name: speedy-antlr-lua-parser
Version: 0.0.1
Summary: UNKNOWN
Home-page: UNKNOWN
License: UNKNOWN
Platform: UNKNOWN
License-File: LICENSE
Requires-Dist: antlr4-python3-runtime (<4.14,>=4.13)
